ParticleDetection/__init__.py
ParticleDetection/modelling/__init__.py
ParticleDetection/modelling/annotations.py
ParticleDetection/modelling/augmentations.py
ParticleDetection/modelling/configs.py
ParticleDetection/modelling/datasets.py
ParticleDetection/modelling/detectron.py
ParticleDetection/modelling/export.py
ParticleDetection/modelling/runners/__init__.py
ParticleDetection/modelling/runners/detection.py
ParticleDetection/modelling/runners/training.py
ParticleDetection/modelling/visualization.py
ParticleDetection/reconstruct_3D/__init__.py
ParticleDetection/reconstruct_3D/calibrate_cameras.py
ParticleDetection/reconstruct_3D/example_calibration/Matlab/gp12.json
ParticleDetection/reconstruct_3D/example_calibration/Matlab/gp34.json
ParticleDetection/reconstruct_3D/example_calibration/Matlab/world_transformation_gp12.json
ParticleDetection/reconstruct_3D/example_calibration/Matlab/world_transformation_old_format_matlab.json
ParticleDetection/reconstruct_3D/example_calibration/OpenCV/gp12.json
ParticleDetection/reconstruct_3D/example_calibration/OpenCV/gp34.json
ParticleDetection/reconstruct_3D/example_calibration/OpenCV/gp34_alt.json
ParticleDetection/reconstruct_3D/match2D.py
ParticleDetection/reconstruct_3D/matchND.py
ParticleDetection/reconstruct_3D/tracking.py
ParticleDetection/reconstruct_3D/visualization.py
ParticleDetection/utils/__init__.py
ParticleDetection/utils/data_conversions.py
ParticleDetection/utils/data_loading.py
ParticleDetection/utils/datasets.py
ParticleDetection/utils/detection.py
ParticleDetection/utils/helper_funcs.py
particledetection-0.4.3.dist-info/LICENSE
particledetection-0.4.3.dist-info/METADATA
particledetection-0.4.3.dist-info/WHEEL
particledetection-0.4.3.dist-info/RECORD
